[
  {
    "id": 1,
    "title": "title",
    "content": "Welcome to world best coding bootcamp!"
  },
  {
    "id": 2,
    "title": "title",
    "content": "Welcome to world best coding bootcamp!"
  },
  {
    "id": 3,
    "title": "title",
    "content": "Welcome to world best coding bootcamp!"
  },
  {
    "id": 4,
    "title": "title",
    "content": "Welcome to world best coding bootcamp!"
  },
  {
    "id": 5,
    "title": "title",
    "content": "Welcome to world best coding bootcamp!"
  },
  {
    "id": 6,
    "title": "title",
    "content": "Welcome to world best coding bootcamp!"
  },
  {
    "id": 7,
    "title": "title",
    "content": "Welcome to world best coding bootcamp!"
  },
  {
    "id": 8,
    "title": "title",
    "content": "Welcome to world best coding bootcamp!"
  },
  {
    "id": 9,
    "title": "title",
    "content": "Welcome to world best coding bootcamp!"
  },
  {
    "id": 10,
    "title": "title",
    "content": "Welcome to world best coding bootcamp!"
  }
]
